{"EURUSD": {"long": 39.0, "short": 61.0}, "GBPUSD": {"long": 56.0, "short": 44.0}, "USDJPY": {"long": 75.0, "short": 25.0}, "GBPJPY": {"long": 52.0, "short": 48.0}, "USDCAD": {"long": 66.0, "short": 34.0}, "EURAUD": {"long": 17.0, "short": 83.0}, "EURJPY": {"long": 78.0, "short": 22.0}, "AUDCAD": {"long": 80.0, "short": 20.0}, "AUDJPY": {"long": 87.0, "short": 13.0}, "AUDNZD": {"long": 66.0, "short": 34.0}, "AUDUSD": {"long": 70.0, "short": 30.0}, "CADJPY": {"long": 81.0, "short": 19.0}, "EURCAD": {"long": 23.0, "short": 77.0}, "EURCHF": {"long": 66.0, "short": 34.0}, "EURCZK": {"long": 63.0, "short": 37.0}, "EURGBP": {"long": 16.0, "short": 84.0}, "EURHUF": {"long": 36.0, "short": 64.0}, "EURNOK": {"long": 50.0, "short": 50.0}, "EURNZD": {"long": 12.0, "short": 88.0}, "EURPLN": {"long": 99.0, "short": 1.0}, "EURSEK": {"long": 14.0, "short": 86.0}, "EURTRY": {"long": 100.0, "short": 0.0}, "GBPCAD": {"long": 77.0, "short": 23.0}, "GBPCHF": {"long": 82.0, "short": 18.0}, "NZDCAD": {"long": 89.0, "short": 11.0}, "NZDJPY": {"long": 90.0, "short": 10.0}, "NZDUSD": {"long": 72.0, "short": 28.0}, "USDCHF": {"long": 58.0, "short": 42.0}, "USDCZK": {"long": 0.0, "short": 100.0}, "USDHUF": {"long": 0.0, "short": 100.0}, "USDMXN": {"long": 61.0, "short": 39.0}, "USDNOK": {"long": 48.0, "short": 52.0}, "USDPLN": {"long": 0.0, "short": 100.0}, "USDSEK": {"long": 51.0, "short": 49.0}, "USDSGD": {"long": 83.0, "short": 17.0}, "USDTHB": {"long": 20.0, "short": 80.0}, "USDTRY": {"long": 100.0, "short": 0.0}, "USDZAR": {"long": 85.0, "short": 15.0}, "CHFJPY": {"long": 80.0, "short": 20.0}, "AUDCHF": {"long": 93.0, "short": 7.0}, "GBPNZD": {"long": 38.0, "short": 62.0}, "NZDCHF": {"long": 87.0, "short": 13.0}, "XAGUSD": {"long": 44.0, "short": 56.0}, "XAUUSD": {"long": 48.0, "short": 52.0}, "CADCHF": {"long": 34.0, "short": 66.0}, "GBPAUD": {"long": 35.0, "short": 65.0}, "SGDJPY": {"long": 100.0, "short": 0.0}, "GBPNOK": {"long": 0.0, "short": 100.0}, "EURZAR": {"long": 99.0, "short": 1.0}, "AUDSGD": {"long": 55.0, "short": 45.0}, "GBPSEK": {"long": 0.0, "short": 100.0}, "CHFSGD": {"long": 92.0, "short": 8.0}, "EURSGD": {"long": 30.0, "short": 70.0}, "GBPSGD": {"long": 14.0, "short": 86.0}, "XAUGBP": {"long": 91.0, "short": 9.0}, "NOKJPY": {"long": 99.0, "short": 1.0}, "ZARJPY": {"long": 93.0, "short": 7.0}, "GBPTRY": {"long": 100.0, "short": 0.0}, "USDRUB": {"long": 0.0, "short": 100.0}, "SEKJPY": {"long": 0.0, "short": 100.0}, "EURMXN": {"long": 100.0, "short": 0.0}, "XAUAUD": {"long": 25.0, "short": 75.0}, "XAUEUR": {"long": 17.0, "short": 84.0}, "XAUJPY": {"long": 19.0, "short": 81.0}, "XAUCHF": {"long": 3.0, "short": 97.0}, "GBPMXN": {"long": 100.0, "short": 0.0}, "XAGAUD": {"long": 50.0, "short": 50.0}, "NOKSEK": {"long": 30.0, "short": 70.0}, "XAGEUR": {"long": 0.0, "short": 100.0}, "XPTUSD": {"long": 47.0, "short": 53.0}, "XPDUSD": {"long": 0.0, "short": 100.0}, "USDCNH": {"long": 0.0, "short": 100.0}}