{
 "USDCHF": {
  "setup": "extended",
  "bias": "Very Bullish",
  "loc": 99
 },
 "USDCAD": {
  "setup": "extended",
  "bias": "Very Bullish",
  "loc": 96
 },
 "NIKKEI": {
  "setup": "extended",
  "bias": "Very Bullish",
  "loc": 95
 },
 "USDJPY": {
  "setup": "extended",
  "bias": "Bullish",
  "loc": 93
 },
 "GBPCAD": {
  "setup": "extended",
  "bias": "Bullish",
  "loc": 91
 },
 "GBPAUD": {
  "setup": "extended",
  "bias": "Bullish",
  "loc": 65
 },
 "GBPCHF": {
  "setup": "extended",
  "bias": "Bullish",
  "loc": 99
 },
 "GBPNZD": {
  "setup": "extended",
  "bias": "Bullish",
  "loc": 98
 },
 "EURCHF": {
  "setup": null,
  "bias": "Neutral",
  "loc": 86
 },
 "NASDAQ": {
  "setup": null,
  "bias": "Neutral",
  "loc": 89
 },
 "EURAUD": {
  "setup": null,
  "bias": "Neutral",
  "loc": 52
 },
 "EURNZD": {
  "setup": null,
  "bias": "Neutral",
  "loc": 92
 },
 "EURCAD": {
  "setup": null,
  "bias": "Neutral",
  "loc": 76
 },
 "GBPJPY": {
  "setup": null,
  "bias": "Neutral",
  "loc": 59
 },
 "AUDNZD": {
  "setup": null,
  "bias": "Neutral",
  "loc": 90
 },
 "AUDCHF": {
  "setup": null,
  "bias": "Neutral",
  "loc": 76
 },
 "NZDCHF": {
  "setup": null,
  "bias": "Neutral",
  "loc": 42
 },
 "CADCHF": {
  "setup": null,
  "bias": "Neutral",
  "loc": 47
 },
 "AUDCAD": {
  "setup": null,
  "bias": "Neutral",
  "loc": 81
 },
 "NZDCAD": {
  "setup": null,
  "bias": "Neutral",
  "loc": 41
 },
 "PLATINUM": {
  "setup": null,
  "bias": "Neutral",
  "loc": 3
 },
 "NZDJPY": {
  "setup": null,
  "bias": "Neutral",
  "loc": 25
 },
 "EURGBP": {
  "setup": null,
  "bias": "Neutral",
  "loc": 5
 },
 "EURJPY": {
  "setup": null,
  "bias": "Neutral",
  "loc": 47
 },
 "CADJPY": {
  "setup": "extended",
  "bias": "Bearish",
  "loc": 12
 },
 "GBPUSD": {
  "setup": "extended",
  "bias": "Bearish",
  "loc": 17
 },
 "AUDJPY": {
  "setup": "mid",
  "bias": "Bearish",
  "loc": 51
 },
 "CHFJPY": {
  "setup": "extended",
  "bias": "Bearish",
  "loc": 26
 },
 "XAUUSD": {
  "setup": "extended",
  "bias": "Bearish",
  "loc": 24
 },
 "EURUSD": {
  "setup": "extended",
  "bias": "Very Bearish",
  "loc": 3
 },
 "NZDUSD": {
  "setup": "extended",
  "bias": "Very Bearish",
  "loc": 0
 },
 "SILVER": {
  "setup": "extended",
  "bias": "Very Bearish",
  "loc": 6
 },
 "AUDUSD": {
  "setup": "extended",
  "bias": "Very Bearish",
  "loc": 8
 }
}