{
 "USDCAD": {
  "setup": "extended",
  "bias": "Bullish",
  "loc": 92
 },
 "UK100": {
  "setup": "extended",
  "bias": "Bullish",
  "loc": 87
 },
 "GBPAUD": {
  "setup": null,
  "bias": "Neutral",
  "loc": 89
 },
 "GBPCAD": {
  "setup": null,
  "bias": "Neutral",
  "loc": 87
 },
 "NIKKEI": {
  "setup": null,
  "bias": "Neutral",
  "loc": 77
 },
 "GBPNZD": {
  "setup": null,
  "bias": "Neutral",
  "loc": 99
 },
 "DAX": {
  "setup": null,
  "bias": "Neutral",
  "loc": 79
 },
 "USDJPY": {
  "setup": null,
  "bias": "Neutral",
  "loc": 85
 },
 "USDCHF": {
  "setup": null,
  "bias": "Neutral",
  "loc": 82
 },
 "GBPJPY": {
  "setup": null,
  "bias": "Neutral",
  "loc": 87
 },
 "EURAUD": {
  "setup": null,
  "bias": "Neutral",
  "loc": 69
 },
 "GBPCHF": {
  "setup": null,
  "bias": "Neutral",
  "loc": 97
 },
 "EURNZD": {
  "setup": null,
  "bias": "Neutral",
  "loc": 81
 },
 "CHFJPY": {
  "setup": null,
  "bias": "Neutral",
  "loc": 34
 },
 "EURCAD": {
  "setup": null,
  "bias": "Neutral",
  "loc": 77
 },
 "NZDCAD": {
  "setup": null,
  "bias": "Neutral",
  "loc": 22
 },
 "XAUUSD": {
  "setup": null,
  "bias": "Neutral",
  "loc": 19
 },
 "GBPUSD": {
  "setup": null,
  "bias": "Neutral",
  "loc": 53
 },
 "EURJPY": {
  "setup": null,
  "bias": "Neutral",
  "loc": 54
 },
 "AUDNZD": {
  "setup": null,
  "bias": "Neutral",
  "loc": 69
 },
 "CADCHF": {
  "setup": null,
  "bias": "Neutral",
  "loc": 42
 },
 "NASDAQ": {
  "setup": null,
  "bias": "Neutral",
  "loc": 38
 },
 "PLATINUM": {
  "setup": null,
  "bias": "Neutral",
  "loc": 18
 },
 "NZDUSD": {
  "setup": null,
  "bias": "Neutral",
  "loc": 14
 },
 "NZDJPY": {
  "setup": null,
  "bias": "Neutral",
  "loc": 22
 },
 "CADJPY": {
  "setup": null,
  "bias": "Neutral",
  "loc": 32
 },
 "AUDCAD": {
  "setup": null,
  "bias": "Neutral",
  "loc": 39
 },
 "NZDCHF": {
  "setup": null,
  "bias": "Neutral",
  "loc": 24
 },
 "EURUSD": {
  "setup": null,
  "bias": "Neutral",
  "loc": 20
 },
 "AUDJPY": {
  "setup": null,
  "bias": "Neutral",
  "loc": 27
 },
 "EURCHF": {
  "setup": null,
  "bias": "Neutral",
  "loc": 73
 },
 "AUDCHF": {
  "setup": null,
  "bias": "Neutral",
  "loc": 32
 },
 "EURGBP": {
  "setup": null,
  "bias": "Neutral",
  "loc": 2
 },
 "SILVER": {
  "setup": null,
  "bias": "Neutral",
  "loc": 11
 },
 "AUDUSD": {
  "setup": "extended",
  "bias": "Bearish",
  "loc": 16
 }
}