{
 "UK100": {
  "setup": "mid",
  "bias": "Bullish",
  "loc": 63
 },
 "USDCAD": {
  "setup": "extended",
  "bias": "Bullish",
  "loc": 87
 },
 "GBPAUD": {
  "setup": null,
  "bias": "Neutral",
  "loc": 91
 },
 "EURCAD": {
  "setup": null,
  "bias": "Neutral",
  "loc": 96
 },
 "GBPCAD": {
  "setup": null,
  "bias": "Neutral",
  "loc": 82
 },
 "XAUUSD": {
  "setup": null,
  "bias": "Neutral",
  "loc": 12
 },
 "USDJPY": {
  "setup": null,
  "bias": "Neutral",
  "loc": 86
 },
 "USDCHF": {
  "setup": null,
  "bias": "Neutral",
  "loc": 83
 },
 "GBPJPY": {
  "setup": null,
  "bias": "Neutral",
  "loc": 93
 },
 "CADJPY": {
  "setup": null,
  "bias": "Neutral",
  "loc": 52
 },
 "CHFJPY": {
  "setup": null,
  "bias": "Neutral",
  "loc": 43
 },
 "EURAUD": {
  "setup": null,
  "bias": "Neutral",
  "loc": 74
 },
 "GBPNZD": {
  "setup": null,
  "bias": "Neutral",
  "loc": 90
 },
 "GBPCHF": {
  "setup": null,
  "bias": "Neutral",
  "loc": 95
 },
 "EURJPY": {
  "setup": null,
  "bias": "Neutral",
  "loc": 69
 },
 "NZDJPY": {
  "setup": null,
  "bias": "Neutral",
  "loc": 34
 },
 "NIKKEI": {
  "setup": null,
  "bias": "Neutral",
  "loc": 56
 },
 "DAX": {
  "setup": null,
  "bias": "Neutral",
  "loc": 54
 },
 "GBPUSD": {
  "setup": null,
  "bias": "Neutral",
  "loc": 50
 },
 "AUDJPY": {
  "setup": null,
  "bias": "Neutral",
  "loc": 33
 },
 "AUDCAD": {
  "setup": null,
  "bias": "Neutral",
  "loc": 30
 },
 "NZDCAD": {
  "setup": null,
  "bias": "Neutral",
  "loc": 28
 },
 "CADCHF": {
  "setup": null,
  "bias": "Neutral",
  "loc": 56
 },
 "NASDAQ": {
  "setup": null,
  "bias": "Neutral",
  "loc": 38
 },
 "NZDUSD": {
  "setup": null,
  "bias": "Neutral",
  "loc": 19
 },
 "AUDNZD": {
  "setup": null,
  "bias": "Neutral",
  "loc": 54
 },
 "NZDCHF": {
  "setup": null,
  "bias": "Neutral",
  "loc": 37
 },
 "PLATINUM": {
  "setup": null,
  "bias": "Neutral",
  "loc": 7
 },
 "EURUSD": {
  "setup": null,
  "bias": "Neutral",
  "loc": 21
 },
 "AUDUSD": {
  "setup": null,
  "bias": "Neutral",
  "loc": 14
 },
 "EURCHF": {
  "setup": null,
  "bias": "Neutral",
  "loc": 72
 },
 "AUDCHF": {
  "setup": null,
  "bias": "Neutral",
  "loc": 33
 },
 "EURGBP": {
  "setup": null,
  "bias": "Neutral",
  "loc": 9
 },
 "EURNZD": {
  "setup": null,
  "bias": "Neutral",
  "loc": 74
 },
 "SILVER": {
  "setup": null,
  "bias": "Neutral",
  "loc": 6
 }
}